{
  "pageIndex": 1,
  "content": [
    {
      "type": "paragraph",
      "words": [
        "CHAPTER",
        " ",
        "16",
        ".",
        " ",
        "The",
        " ",
        "Ship",
        "."
      ]
    },
    {
      "type": "paragraph",
      "words": [
        "CHAPTER",
        " ",
        "17",
        ".",
        " ",
        "The",
        " ",
        "Ramadan",
        "."
      ]
    },
    {
      "type": "paragraph",
      "words": [
        "CHAPTER",
        " ",
        "18",
        ".",
        " ",
        "His",
        " ",
        "Mark",
        "."
      ]
    },
    {
      "type": "paragraph",
      "words": [
        "CHAPTER",
        " ",
        "19",
        ".",
        " ",
        "The",
        " ",
        "Prophet",
        "."
      ]
    },
    {
      "type": "paragraph",
      "words": [
        "CHAPTER",
        " ",
        "20",
        ".",
        " ",
        "All",
        " ",
        "Astir",
        "."
      ]
    },
    {
      "type": "paragraph",
      "words": [
        "CHAPTER",
        " ",
        "21",
        ".",
        " ",
        "Going",
        " ",
        "Aboard",
        "."
      ]
    },
    {
      "type": "paragraph",
      "words": [
        "CHAPTER",
        " ",
        "22",
        ".",
        " ",
        "Merry",
        " ",
        "Christmas",
        "."
      ]
    },
    {
      "type": "paragraph",
      "words": [
        "CHAPTER",
        " ",
        "23",
        ".",
        " ",
        "The",
        " ",
        "Lee",
        " ",
        "Shore",
        "."
      ]
    },
    {
      "type": "paragraph",
      "words": [
        "CHAPTER",
        " ",
        "24",
        ".",
        " ",
        "The",
        " ",
        "Advocate",
        "."
      ]
    },
    {
      "type": "paragraph",
      "words": [
        "CHAPTER",
        " ",
        "25",
        ".",
        " ",
        "Postscript",
        "."
      ]
    },
    {
      "type": "paragraph",
      "words": [
        "CHAPTER",
        " ",
        "26",
        ".",
        " ",
        "Knights",
        " ",
        "and",
        " ",
        "Squires",
        "."
      ]
    },
    {
      "type": "paragraph",
      "words": [
        "CHAPTER",
        " ",
        "27",
        ".",
        " ",
        "Knights",
        " ",
        "and",
        " ",
        "Squires",
        "."
      ]
    },
    {
      "type": "paragraph",
      "words": [
        "CHAPTER",
        " ",
        "28",
        ".",
        " ",
        "Ahab",
        "."
      ]
    },
    {
      "type": "paragraph",
      "words": [
        "CHAPTER",
        " ",
        "29",
        ".",
        " ",
        "Enter",
        " ",
        "Ahab",
        ";",
        " ",
        "to",
        " ",
        "Him",
        ",",
        " ",
        "Stubb",
        "."
      ]
    },
    {
      "type": "paragraph",
      "words": [
        "CHAPTER",
        " ",
        "30",
        ".",
        " ",
        "The",
        " ",
        "Pipe",
        "."
      ]
    },
    {
      "type": "paragraph",
      "words": [
        "CHAPTER",
        " ",
        "31",
        ".",
        " ",
        "Queen",
        " ",
        "Mab",
        "."
      ]
    },
    {
      "type": "paragraph",
      "words": [
        "CHAPTER",
        " ",
        "32",
        ".",
        " ",
        "Cetology",
        "."
      ]
    },
    {
      "type": "paragraph",
      "words": [
        "CHAPTER",
        " ",
        "33",
        ".",
        " ",
        "The",
        " ",
        "Specksnyder",
        "."
      ]
    },
    {
      "type": "paragraph",
      "words": [
        "CHAPTER",
        " ",
        "34",
        ".",
        " ",
        "The",
        " ",
        "Cabin",
        "-",
        "Table",
        "."
      ]
    },
    {
      "type": "paragraph",
      "words": [
        "CHAPTER",
        " ",
        "35",
        ".",
        " ",
        "The",
        " ",
        "Mast",
        "-",
        "Head",
        "."
      ]
    },
    {
      "type": "paragraph",
      "words": [
        "CHAPTER",
        " ",
        "36",
        ".",
        " ",
        "The",
        " ",
        "Quarter",
        "-",
        "Deck",
        "."
      ]
    },
    {
      "type": "paragraph",
      "words": [
        "CHAPTER",
        " ",
        "37",
        ".",
        " ",
        "Sunset",
        "."
      ]
    },
    {
      "type": "paragraph",
      "words": [
        "CHAPTER",
        " ",
        "38",
        ".",
        " ",
        "Dusk",
        "."
      ]
    },
    {
      "type": "paragraph",
      "words": [
        "CHAPTER",
        " ",
        "39",
        ".",
        " ",
        "First",
        " ",
        "Night",
        "-",
        "Watch",
        "."
      ]
    },
    {
      "type": "paragraph",
      "words": [
        "CHAPTER",
        " ",
        "40",
        ".",
        " ",
        "Midnight",
        ",",
        " ",
        "Forecastle",
        "."
      ]
    },
    {
      "type": "paragraph",
      "words": [
        "CHAPTER",
        " ",
        "41",
        ".",
        " ",
        "Moby",
        " ",
        "Dick",
        "."
      ]
    },
    {
      "type": "paragraph",
      "words": [
        "CHAPTER",
        " ",
        "42",
        ".",
        " ",
        "The",
        " ",
        "Whiteness",
        " ",
        "of",
        " ",
        "the",
        " ",
        "Whale",
        "."
      ]
    }
  ]
}