{
  "pageIndex": 3,
  "content": [
    {
      "type": "paragraph",
      "words": [
        "CHAPTER",
        " ",
        "62",
        ".",
        " ",
        "The",
        " ",
        "Dart",
        "."
      ]
    },
    {
      "type": "paragraph",
      "words": [
        "CHAPTER",
        " ",
        "63",
        ".",
        " ",
        "The",
        " ",
        "Crotch",
        "."
      ]
    },
    {
      "type": "paragraph",
      "words": [
        "CHAPTER",
        " ",
        "64",
        ".",
        " ",
        "Stubb’s",
        " ",
        "Supper",
        "."
      ]
    },
    {
      "type": "paragraph",
      "words": [
        "CHAPTER",
        " ",
        "65",
        ".",
        " ",
        "The",
        " ",
        "Whale",
        " ",
        "as",
        " ",
        "a",
        " ",
        "Dish",
        "."
      ]
    },
    {
      "type": "paragraph",
      "words": [
        "CHAPTER",
        " ",
        "66",
        ".",
        " ",
        "The",
        " ",
        "Shark",
        " ",
        "Massacre",
        "."
      ]
    },
    {
      "type": "paragraph",
      "words": [
        "CHAPTER",
        " ",
        "67",
        ".",
        " ",
        "Cutting",
        " ",
        "In",
        "."
      ]
    },
    {
      "type": "paragraph",
      "words": [
        "CHAPTER",
        " ",
        "68",
        ".",
        " ",
        "The",
        " ",
        "Blanket",
        "."
      ]
    },
    {
      "type": "paragraph",
      "words": [
        "CHAPTER",
        " ",
        "69",
        ".",
        " ",
        "The",
        " ",
        "Funeral",
        "."
      ]
    },
    {
      "type": "paragraph",
      "words": [
        "CHAPTER",
        " ",
        "70",
        ".",
        " ",
        "The",
        " ",
        "Sphynx",
        "."
      ]
    },
    {
      "type": "paragraph",
      "words": [
        "CHAPTER",
        " ",
        "71",
        ".",
        " ",
        "The",
        " ",
        "Jeroboam’s",
        " ",
        "Story",
        "."
      ]
    },
    {
      "type": "paragraph",
      "words": [
        "CHAPTER",
        " ",
        "72",
        ".",
        " ",
        "The",
        " ",
        "Monkey",
        "-",
        "Rope",
        "."
      ]
    },
    {
      "type": "paragraph",
      "words": [
        "CHAPTER",
        " ",
        "73",
        ".",
        " ",
        "Stubb",
        " ",
        "and",
        " ",
        "Flask",
        " ",
        "kill",
        " ",
        "a",
        " ",
        "Right",
        " ",
        "Whale",
        ";",
        "         ",
        "and",
        " ",
        "Then",
        " ",
        "Have",
        " ",
        "a",
        " ",
        "Talk",
        " ",
        "over",
        " ",
        "Him",
        "."
      ]
    },
    {
      "type": "paragraph",
      "words": [
        "CHAPTER",
        " ",
        "74",
        ".",
        " ",
        "The",
        " ",
        "Sperm",
        " ",
        "Whale’s",
        " ",
        "Head",
        "—",
        "Contrasted",
        "         ",
        "View",
        "."
      ]
    },
    {
      "type": "paragraph",
      "words": [
        "CHAPTER",
        " ",
        "75",
        ".",
        " ",
        "The",
        " ",
        "Right",
        " ",
        "Whale’s",
        " ",
        "Head",
        "—",
        "Contrasted",
        "         ",
        "View",
        "."
      ]
    },
    {
      "type": "paragraph",
      "words": [
        "CHAPTER",
        " ",
        "76",
        ".",
        " ",
        "The",
        " ",
        "Battering",
        "-",
        "Ram",
        "."
      ]
    },
    {
      "type": "paragraph",
      "words": [
        "CHAPTER",
        " ",
        "77",
        ".",
        " ",
        "The",
        " ",
        "Great",
        " ",
        "Heidelburgh",
        " ",
        "Tun",
        "."
      ]
    },
    {
      "type": "paragraph",
      "words": [
        "CHAPTER",
        " ",
        "78",
        ".",
        " ",
        "Cistern",
        " ",
        "and",
        " ",
        "Buckets",
        "."
      ]
    },
    {
      "type": "paragraph",
      "words": [
        "CHAPTER",
        " ",
        "79",
        ".",
        " ",
        "The",
        " ",
        "Prairie",
        "."
      ]
    },
    {
      "type": "paragraph",
      "words": [
        "CHAPTER",
        " ",
        "80",
        ".",
        " ",
        "The",
        " ",
        "Nut",
        "."
      ]
    },
    {
      "type": "paragraph",
      "words": [
        "CHAPTER",
        " ",
        "81",
        ".",
        " ",
        "The",
        " ",
        "Pequod",
        " ",
        "Meets",
        " ",
        "The",
        " ",
        "Virgin",
        "."
      ]
    },
    {
      "type": "paragraph",
      "words": [
        "CHAPTER",
        " ",
        "82",
        ".",
        " ",
        "The",
        " ",
        "Honor",
        " ",
        "and",
        " ",
        "Glory",
        " ",
        "of",
        " ",
        "Whaling",
        "."
      ]
    }
  ]
}