{
  "pageIndex": 928,
  "content": [
    {
      "type": "paragraph",
      "words": [
        "For",
        " ",
        "a",
        " ",
        "moment",
        ",",
        " ",
        "the",
        " ",
        "old",
        " ",
        "blacksmith",
        " ",
        "eyed",
        " ",
        "the",
        " ",
        "razors",
        " ",
        "as",
        " ",
        "though",
        " ",
        "he",
        " ",
        "would",
        " ",
        "fain",
        "       ",
        "not",
        " ",
        "use",
        " ",
        "them",
        "."
      ]
    },
    {
      "type": "paragraph",
      "words": [
        "“",
        "Take",
        " ",
        "them",
        ",",
        " ",
        "man",
        ",",
        " ",
        "I",
        " ",
        "have",
        " ",
        "no",
        " ",
        "need",
        " ",
        "for",
        " ",
        "them",
        ";",
        " ",
        "for",
        " ",
        "I",
        " ",
        "now",
        " ",
        "neither",
        " ",
        "shave",
        ",",
        " ",
        "sup",
        ",",
        "       ",
        "nor",
        " ",
        "pray",
        " ",
        "till",
        "—",
        "but",
        " ",
        "here",
        "—",
        "to",
        " ",
        "work",
        "!",
        "”"
      ]
    },
    {
      "type": "paragraph",
      "words": [
        "Fashioned",
        " ",
        "at",
        " ",
        "last",
        " ",
        "into",
        " ",
        "an",
        " ",
        "arrowy",
        " ",
        "shape",
        ",",
        " ",
        "and",
        " ",
        "welded",
        " ",
        "by",
        " ",
        "Perth",
        " ",
        "to",
        " ",
        "the",
        " ",
        "shank",
        ",",
        "       ",
        "the",
        " ",
        "steel",
        " ",
        "soon",
        " ",
        "pointed",
        " ",
        "the",
        " ",
        "end",
        " ",
        "of",
        " ",
        "the",
        " ",
        "iron",
        ";",
        " ",
        "and",
        " ",
        "as",
        " ",
        "the",
        " ",
        "blacksmith",
        " ",
        "was",
        "       ",
        "about",
        " ",
        "giving",
        " ",
        "the",
        " ",
        "barbs",
        " ",
        "their",
        " ",
        "final",
        " ",
        "heat",
        ",",
        " ",
        "prior",
        " ",
        "to",
        " ",
        "tempering",
        " ",
        "them",
        ",",
        " ",
        "he",
        " ",
        "cried",
        "       ",
        "to",
        " ",
        "Ahab",
        " ",
        "to",
        " ",
        "place",
        " ",
        "the",
        " ",
        "water",
        "-",
        "cask",
        " ",
        "near",
        "."
      ]
    },
    {
      "type": "paragraph",
      "words": [
        "“",
        "No",
        ",",
        " ",
        "no",
        "—",
        "no",
        " ",
        "water",
        " ",
        "for",
        " ",
        "that",
        ";",
        " ",
        "I",
        " ",
        "want",
        " ",
        "it",
        " ",
        "of",
        " ",
        "the",
        " ",
        "true",
        " ",
        "death",
        "-",
        "temper",
        ".",
        " ",
        "Ahoy",
        ",",
        "       ",
        "there",
        "!",
        " ",
        "Tashtego",
        ",",
        " ",
        "Queequeg",
        ",",
        " ",
        "Daggoo",
        "!",
        " ",
        "What",
        " ",
        "say",
        " ",
        "ye",
        ",",
        " ",
        "pagans",
        "!",
        " ",
        "Will",
        " ",
        "ye",
        " ",
        "give",
        " ",
        "me",
        " ",
        "as",
        "       ",
        "much",
        " ",
        "blood",
        " ",
        "as",
        " ",
        "will",
        " ",
        "cover",
        " ",
        "this",
        " ",
        "barb",
        "?",
        "”",
        " ",
        "holding",
        " ",
        "it",
        " ",
        "high",
        " ",
        "up",
        ".",
        " ",
        "A",
        " ",
        "cluster",
        " ",
        "of",
        " ",
        "dark",
        "       ",
        "nods",
        " ",
        "replied",
        ",",
        " ",
        "Yes",
        ".",
        " ",
        "Three",
        " ",
        "punctures",
        " ",
        "were",
        " ",
        "made",
        " ",
        "in",
        " ",
        "the",
        " ",
        "heathen",
        " ",
        "flesh",
        ",",
        " ",
        "and",
        " ",
        "the",
        "       ",
        "White",
        " ",
        "Whale’s",
        " ",
        "barbs",
        " ",
        "were",
        " ",
        "then",
        " ",
        "tempered",
        "."
      ]
    }
  ]
}