{
  "pageIndex": 352,
  "content": [
    {
      "type": "paragraph",
      "words": [
        "I",
        " ",
        "was",
        " ",
        "touched",
        " ",
        "by",
        " ",
        "the",
        " ",
        "tenderness",
        " ",
        "of",
        " ",
        "his",
        " ",
        "tone",
        ",",
        " ",
        "and",
        " ",
        "asked",
        " ",
        "why",
        "."
      ]
    },
    {
      "type": "paragraph",
      "words": [
        "“",
        "Because",
        " ",
        "I",
        " ",
        "know",
        "!",
        "”"
      ]
    },
    {
      "type": "paragraph",
      "words": [
        "And",
        " ",
        "now",
        " ",
        "we",
        " ",
        "are",
        " ",
        "all",
        " ",
        "scattered",
        ";",
        " ",
        "and",
        " ",
        "for",
        " ",
        "many",
        " ",
        "a",
        " ",
        "long",
        " ",
        "day",
        " ",
        "loneliness",
        " ",
        "will",
        " ",
        "sit",
        " ",
        "over",
        " ",
        "our",
        " ",
        "roofs",
        " ",
        "with",
        " ",
        "brooding",
        " ",
        "wings",
        ".",
        " ",
        "Lucy",
        " ",
        "lies",
        " ",
        "in",
        " ",
        "the",
        " ",
        "tomb",
        " ",
        "of",
        " ",
        "her",
        " ",
        "kin",
        ",",
        " ",
        "a",
        " ",
        "lordly",
        " ",
        "death",
        "-",
        "house",
        " ",
        "in",
        " ",
        "a",
        " ",
        "lonely",
        " ",
        "churchyard",
        ",",
        " ",
        "away",
        " ",
        "from",
        " ",
        "teeming",
        " ",
        "London",
        ";",
        " ",
        "where",
        " ",
        "the",
        " ",
        "air",
        " ",
        "is",
        " ",
        "fresh",
        ",",
        " ",
        "and",
        " ",
        "the",
        " ",
        "sun",
        " ",
        "rises",
        " ",
        "over",
        " ",
        "Hampstead",
        " ",
        "Hill",
        ",",
        " ",
        "and",
        " ",
        "where",
        " ",
        "wild",
        " ",
        "flowers",
        " ",
        "grow",
        " ",
        "of",
        " ",
        "their",
        " ",
        "own",
        " ",
        "accord",
        "."
      ]
    },
    {
      "type": "paragraph",
      "words": [
        "So",
        " ",
        "I",
        " ",
        "can",
        " ",
        "finish",
        " ",
        "this",
        " ",
        "diary",
        ";",
        " ",
        "and",
        " ",
        "God",
        " ",
        "only",
        " ",
        "knows",
        " ",
        "if",
        " ",
        "I",
        " ",
        "shall",
        " ",
        "ever",
        " ",
        "begin",
        " ",
        "another",
        ".",
        " ",
        "If",
        " ",
        "I",
        " ",
        "do",
        ",",
        " ",
        "or",
        " ",
        "if",
        " ",
        "I",
        " ",
        "even",
        " ",
        "open",
        " ",
        "this",
        " ",
        "again",
        ",",
        " ",
        "it",
        " ",
        "will",
        " ",
        "be",
        " ",
        "to",
        " ",
        "deal",
        " ",
        "with",
        " ",
        "different",
        " ",
        "people",
        " ",
        "and",
        " ",
        "different",
        " ",
        "themes",
        ";",
        " ",
        "for",
        " ",
        "here",
        " ",
        "at",
        " ",
        "the",
        " ",
        "end",
        ",",
        " ",
        "where",
        " ",
        "the",
        " ",
        "romance",
        " ",
        "of",
        " ",
        "my",
        " ",
        "life",
        " ",
        "is",
        " ",
        "told",
        ",",
        " ",
        "ere",
        " ",
        "I",
        " ",
        "go",
        " ",
        "back",
        " ",
        "to",
        " ",
        "take",
        " ",
        "up",
        " ",
        "the",
        " ",
        "thread",
        " ",
        "of",
        " ",
        "my",
        " ",
        "life",
        "-",
        "work",
        ",",
        " ",
        "I",
        " ",
        "say",
        " ",
        "sadly",
        " ",
        "and",
        " ",
        "without",
        " ",
        "hope",
        ","
      ]
    }
  ]
}