{
  "pageIndex": 547,
  "content": [
    {
      "type": "paragraph",
      "words": [
        "I",
        " ",
        "think",
        " ",
        "that",
        " ",
        "through",
        " ",
        "the",
        " ",
        "cloudiness",
        " ",
        "of",
        " ",
        "his",
        " ",
        "insanity",
        " ",
        "he",
        " ",
        "saw",
        " ",
        "some",
        " ",
        "antagonism",
        " ",
        "in",
        " ",
        "me",
        ",",
        " ",
        "for",
        " ",
        "he",
        " ",
        "at",
        " ",
        "once",
        " ",
        "fell",
        " ",
        "back",
        " ",
        "on",
        " ",
        "the",
        " ",
        "last",
        " ",
        "refuge",
        " ",
        "of",
        " ",
        "such",
        " ",
        "as",
        " ",
        "he",
        "—",
        "a",
        " ",
        "dogged",
        " ",
        "silence",
        ".",
        " ",
        "After",
        " ",
        "a",
        " ",
        "short",
        " ",
        "time",
        " ",
        "I",
        " ",
        "saw",
        " ",
        "that",
        " ",
        "for",
        " ",
        "the",
        " ",
        "present",
        " ",
        "it",
        " ",
        "was",
        " ",
        "useless",
        " ",
        "to",
        " ",
        "speak",
        " ",
        "to",
        " ",
        "him",
        ".",
        " ",
        "He",
        " ",
        "was",
        " ",
        "sulky",
        ",",
        " ",
        "and",
        " ",
        "so",
        " ",
        "I",
        " ",
        "came",
        " ",
        "away",
        "."
      ]
    },
    {
      "type": "paragraph",
      "words": [
        "Later",
        " ",
        "in",
        " ",
        "the",
        " ",
        "day",
        " ",
        "he",
        " ",
        "sent",
        " ",
        "for",
        " ",
        "me",
        ".",
        " ",
        "Ordinarily",
        " ",
        "I",
        " ",
        "would",
        " ",
        "not",
        " ",
        "have",
        " ",
        "come",
        " ",
        "without",
        " ",
        "special",
        " ",
        "reason",
        ",",
        " ",
        "but",
        " ",
        "just",
        " ",
        "at",
        " ",
        "present",
        " ",
        "I",
        " ",
        "am",
        " ",
        "so",
        " ",
        "interested",
        " ",
        "in",
        " ",
        "him",
        " ",
        "that",
        " ",
        "I",
        " ",
        "would",
        " ",
        "gladly",
        " ",
        "make",
        " ",
        "an",
        " ",
        "effort",
        ".",
        " ",
        "Besides",
        ",",
        " ",
        "I",
        " ",
        "am",
        " ",
        "glad",
        " ",
        "to",
        " ",
        "have",
        " ",
        "anything",
        " ",
        "to",
        " ",
        "help",
        " ",
        "to",
        " ",
        "pass",
        " ",
        "the",
        " ",
        "time",
        ".",
        " ",
        "Harker",
        " ",
        "is",
        " ",
        "out",
        ",",
        " ",
        "following",
        " ",
        "up",
        " ",
        "clues",
        ";",
        " ",
        "and",
        " ",
        "so",
        " ",
        "are",
        " ",
        "Lord",
        " ",
        "Godalming",
        " ",
        "and",
        " ",
        "Quincey",
        ".",
        " ",
        "Van",
        " ",
        "Helsing",
        " ",
        "sits",
        " ",
        "in",
        " ",
        "my",
        " ",
        "study",
        " ",
        "poring",
        " ",
        "over",
        " ",
        "the",
        " ",
        "record",
        " ",
        "prepared",
        " ",
        "by",
        " ",
        "the",
        " ",
        "Harkers",
        ";",
        " ",
        "he",
        " ",
        "seems",
        " ",
        "to",
        " ",
        "think",
        " ",
        "that",
        " ",
        "by",
        " ",
        "accurate",
        " ",
        "knowledge",
        " ",
        "of",
        " ",
        "all",
        " ",
        "details",
        " ",
        "he",
        " ",
        "will",
        " ",
        "light",
        " ",
        "upon",
        " ",
        "some",
        " ",
        "clue",
        ".",
        " ",
        "He",
        " ",
        "does",
        " ",
        "not",
        " ",
        "wish",
        " ",
        "to",
        " ",
        "be",
        " ",
        "disturbed",
        " ",
        "in",
        " ",
        "the",
        " ",
        "work",
        ",",
        " ",
        "without",
        " ",
        "cause",
        ".",
        " ",
        "I",
        " ",
        "would",
        " ",
        "have",
        " ",
        "taken",
        " ",
        "him",
        " ",
        "with",
        " ",
        "me",
        " ",
        "to",
        " ",
        "see",
        " ",
        "the",
        " ",
        "patient",
        ",",
        " ",
        "only",
        " ",
        "I",
        " ",
        "thought",
        " ",
        "that",
        " ",
        "after",
        " ",
        "his",
        " ",
        "last",
        " ",
        "repulse",
        " ",
        "he",
        " ",
        "might",
        " ",
        "not",
        " ",
        "care",
        " ",
        "to",
        " ",
        "go",
        " ",
        "again",
        ".",
        " ",
        "There",
        " ",
        "was",
        " ",
        "also",
        " ",
        "another",
        " ",
        "reason",
        ":",
        " ",
        "Renfield",
        " ",
        "might",
        " ",
        "not",
        " ",
        "speak",
        " ",
        "so",
        " ",
        "freely",
        " ",
        "before",
        " ",
        "a",
        " ",
        "third",
        " ",
        "person",
        " ",
        "as",
        " ",
        "when",
        " ",
        "he",
        " ",
        "and",
        " ",
        "I",
        " ",
        "were",
        " ",
        "alone",
        "."
      ]
    }
  ]
}