{
  "pageIndex": 259,
  "content": [
    {
      "type": "paragraph",
      "words": [
        "The",
        " ",
        "sound",
        " ",
        "came",
        " ",
        "steadily",
        " ",
        "nearer",
        ";",
        " ",
        "and",
        " ",
        "in",
        " ",
        "advance",
        " ",
        "of",
        " ",
        "it",
        " ",
        "came",
        " ",
        "this",
        " ",
        "ghastly",
        " ",
        "thought",
        ",",
        " ",
        "“",
        "The",
        " ",
        "crocodile",
        " ",
        "is",
        " ",
        "about",
        " ",
        "to",
        " ",
        "board",
        " ",
        "the",
        " ",
        "ship",
        "!",
        "”"
      ]
    },
    {
      "type": "paragraph",
      "words": [
        "Even",
        " ",
        "the",
        " ",
        "iron",
        " ",
        "claw",
        " ",
        "hung",
        " ",
        "inactive",
        ";",
        " ",
        "as",
        " ",
        "if",
        " ",
        "knowing",
        " ",
        "that",
        " ",
        "it",
        " ",
        "was",
        " ",
        "no",
        " ",
        "intrinsic",
        " ",
        "part",
        " ",
        "of",
        " ",
        "what",
        " ",
        "the",
        " ",
        "attacking",
        " ",
        "force",
        " ",
        "wanted",
        ".",
        " ",
        "Left",
        " ",
        "so",
        " ",
        "fearfully",
        " ",
        "alone",
        ",",
        " ",
        "any",
        " ",
        "other",
        " ",
        "man",
        " ",
        "would",
        " ",
        "have",
        " ",
        "lain",
        " ",
        "with",
        " ",
        "his",
        " ",
        "eyes",
        " ",
        "shut",
        " ",
        "where",
        " ",
        "he",
        " ",
        "fell",
        ":",
        " ",
        "but",
        " ",
        "the",
        " ",
        "gigantic",
        " ",
        "brain",
        " ",
        "of",
        " ",
        "Hook",
        " ",
        "was",
        " ",
        "still",
        " ",
        "working",
        ",",
        " ",
        "and",
        " ",
        "under",
        " ",
        "its",
        " ",
        "guidance",
        " ",
        "he",
        " ",
        "crawled",
        " ",
        "on",
        " ",
        "the",
        " ",
        "knees",
        " ",
        "along",
        " ",
        "the",
        " ",
        "deck",
        " ",
        "as",
        " ",
        "far",
        " ",
        "from",
        " ",
        "the",
        " ",
        "sound",
        " ",
        "as",
        " ",
        "he",
        " ",
        "could",
        " ",
        "go",
        ".",
        " ",
        "The",
        " ",
        "pirates",
        " ",
        "respectfully",
        " ",
        "cleared",
        " ",
        "a",
        " ",
        "passage",
        " ",
        "for",
        " ",
        "him",
        ",",
        " ",
        "and",
        " ",
        "it",
        " ",
        "was",
        " ",
        "only",
        " ",
        "when",
        " ",
        "he",
        " ",
        "brought",
        " ",
        "up",
        " ",
        "against",
        " ",
        "the",
        " ",
        "bulwarks",
        " ",
        "that",
        " ",
        "he",
        " ",
        "spoke",
        "."
      ]
    },
    {
      "type": "paragraph",
      "words": [
        "“",
        "Hide",
        " ",
        "me",
        "!",
        "”",
        " ",
        "he",
        " ",
        "cried",
        " ",
        "hoarsely",
        "."
      ]
    },
    {
      "type": "paragraph",
      "words": [
        "They",
        " ",
        "gathered",
        " ",
        "round",
        " ",
        "him",
        ",",
        " ",
        "all",
        " ",
        "eyes",
        " ",
        "averted",
        " ",
        "from",
        " ",
        "the",
        " ",
        "thing",
        " ",
        "that",
        " ",
        "was",
        " ",
        "coming",
        " ",
        "aboard",
        ".",
        " ",
        "They",
        " ",
        "had",
        " ",
        "no",
        " ",
        "thought",
        " ",
        "of",
        " ",
        "fighting",
        " ",
        "it",
        ".",
        " ",
        "It",
        " ",
        "was",
        " ",
        "Fate",
        "."
      ]
    }
  ]
}