{
  "pageIndex": 203,
  "content": [
    {
      "type": "paragraph",
      "words": [
        "“",
        "I",
        " ",
        "do",
        " ",
        "like",
        " ",
        "a",
        " ",
        "mother’s",
        " ",
        "love",
        ",",
        "”",
        " ",
        "said",
        " ",
        "Tootles",
        ",",
        " ",
        "hitting",
        " ",
        "Nibs",
        " ",
        "with",
        " ",
        "a",
        " ",
        "pillow",
        ".",
        " ",
        "“",
        "Do",
        " ",
        "you",
        " ",
        "like",
        " ",
        "a",
        " ",
        "mother’s",
        " ",
        "love",
        ",",
        " ",
        "Nibs",
        "?",
        "”"
      ]
    },
    {
      "type": "paragraph",
      "words": [
        "“",
        "I",
        " ",
        "do",
        " ",
        "just",
        ",",
        "”",
        " ",
        "said",
        " ",
        "Nibs",
        ",",
        " ",
        "hitting",
        " ",
        "back",
        "."
      ]
    },
    {
      "type": "paragraph",
      "words": [
        "“",
        "You",
        " ",
        "see",
        ",",
        "”",
        " ",
        "Wendy",
        " ",
        "said",
        " ",
        "complacently",
        ",",
        " ",
        "“",
        "our",
        " ",
        "heroine",
        " ",
        "knew",
        " ",
        "that",
        " ",
        "the",
        " ",
        "mother",
        " ",
        "would",
        " ",
        "always",
        " ",
        "leave",
        " ",
        "the",
        " ",
        "window",
        " ",
        "open",
        " ",
        "for",
        " ",
        "her",
        " ",
        "children",
        " ",
        "to",
        " ",
        "fly",
        " ",
        "back",
        " ",
        "by",
        ";",
        " ",
        "so",
        " ",
        "they",
        " ",
        "stayed",
        " ",
        "away",
        " ",
        "for",
        " ",
        "years",
        " ",
        "and",
        " ",
        "had",
        " ",
        "a",
        " ",
        "lovely",
        " ",
        "time",
        ".",
        "”"
      ]
    },
    {
      "type": "paragraph",
      "words": [
        "“",
        "Did",
        " ",
        "they",
        " ",
        "ever",
        " ",
        "go",
        " ",
        "back",
        "?",
        "”"
      ]
    },
    {
      "type": "paragraph",
      "words": [
        "“",
        "Let",
        " ",
        "us",
        " ",
        "now",
        ",",
        "”",
        " ",
        "said",
        " ",
        "Wendy",
        ",",
        " ",
        "bracing",
        " ",
        "herself",
        " ",
        "up",
        " ",
        "for",
        " ",
        "her",
        " ",
        "finest",
        " ",
        "effort",
        ",",
        " ",
        "“",
        "take",
        " ",
        "a",
        " ",
        "peep",
        " ",
        "into",
        " ",
        "the",
        " ",
        "future",
        ";",
        "”",
        " ",
        "and",
        " ",
        "they",
        " ",
        "all",
        " ",
        "gave",
        " ",
        "themselves",
        " ",
        "the",
        " ",
        "twist",
        " ",
        "that",
        " ",
        "makes",
        " ",
        "peeps",
        " ",
        "into",
        " ",
        "the",
        " ",
        "future",
        " ",
        "easier",
        ".",
        " ",
        "“",
        "Years",
        " ",
        "have",
        " ",
        "rolled",
        " ",
        "by",
        ",",
        " ",
        "and",
        " ",
        "who",
        " ",
        "is",
        " ",
        "this",
        " ",
        "elegant",
        " ",
        "lady",
        " ",
        "of",
        " ",
        "uncertain",
        " ",
        "age",
        " ",
        "alighting",
        " ",
        "at",
        " ",
        "London",
        " ",
        "Station",
        "?",
        "”"
      ]
    }
  ]
}