{
  "pageIndex": 102,
  "content": [
    {
      "type": "paragraph",
      "words": [
        "The",
        " ",
        "redskins",
        " ",
        "disappear",
        " ",
        "as",
        " ",
        "they",
        " ",
        "have",
        " ",
        "come",
        " ",
        "like",
        " ",
        "shadows",
        ",",
        " ",
        "and",
        " ",
        "soon",
        " ",
        "their",
        " ",
        "place",
        " ",
        "is",
        " ",
        "taken",
        " ",
        "by",
        " ",
        "the",
        " ",
        "beasts",
        ",",
        " ",
        "a",
        " ",
        "great",
        " ",
        "and",
        " ",
        "motley",
        " ",
        "procession",
        ":",
        " ",
        "lions",
        ",",
        " ",
        "tigers",
        ",",
        " ",
        "bears",
        ",",
        " ",
        "and",
        " ",
        "the",
        " ",
        "innumerable",
        " ",
        "smaller",
        " ",
        "savage",
        " ",
        "things",
        " ",
        "that",
        " ",
        "flee",
        " ",
        "from",
        " ",
        "them",
        ",",
        " ",
        "for",
        " ",
        "every",
        " ",
        "kind",
        " ",
        "of",
        " ",
        "beast",
        ",",
        " ",
        "and",
        ",",
        " ",
        "more",
        " ",
        "particularly",
        ",",
        " ",
        "all",
        " ",
        "the",
        " ",
        "man",
        "-",
        "eaters",
        ",",
        " ",
        "live",
        " ",
        "cheek",
        " ",
        "by",
        " ",
        "jowl",
        " ",
        "on",
        " ",
        "the",
        " ",
        "favoured",
        " ",
        "island",
        ".",
        " ",
        "Their",
        " ",
        "tongues",
        " ",
        "are",
        " ",
        "hanging",
        " ",
        "out",
        ",",
        " ",
        "they",
        " ",
        "are",
        " ",
        "hungry",
        " ",
        "to",
        "-",
        "night",
        "."
      ]
    },
    {
      "type": "paragraph",
      "words": [
        "When",
        " ",
        "they",
        " ",
        "have",
        " ",
        "passed",
        ",",
        " ",
        "comes",
        " ",
        "the",
        " ",
        "last",
        " ",
        "figure",
        " ",
        "of",
        " ",
        "all",
        ",",
        " ",
        "a",
        " ",
        "gigantic",
        " ",
        "crocodile",
        ".",
        " ",
        "We",
        " ",
        "shall",
        " ",
        "see",
        " ",
        "for",
        " ",
        "whom",
        " ",
        "she",
        " ",
        "is",
        " ",
        "looking",
        " ",
        "presently",
        "."
      ]
    },
    {
      "type": "paragraph",
      "words": [
        "The",
        " ",
        "crocodile",
        " ",
        "passes",
        ",",
        " ",
        "but",
        " ",
        "soon",
        " ",
        "the",
        " ",
        "boys",
        " ",
        "appear",
        " ",
        "again",
        ",",
        " ",
        "for",
        " ",
        "the",
        " ",
        "procession",
        " ",
        "must",
        " ",
        "continue",
        " ",
        "indefinitely",
        " ",
        "until",
        " ",
        "one",
        " ",
        "of",
        " ",
        "the",
        " ",
        "parties",
        " ",
        "stops",
        " ",
        "or",
        " ",
        "changes",
        " ",
        "its",
        " ",
        "pace",
        ".",
        " ",
        "Then",
        " ",
        "quickly",
        " ",
        "they",
        " ",
        "will",
        " ",
        "be",
        " ",
        "on",
        " ",
        "top",
        " ",
        "of",
        " ",
        "each",
        " ",
        "other",
        "."
      ]
    }
  ]
}