{
  "pageIndex": 114,
  "content": [
    {
      "type": "paragraph",
      "words": [
        "“",
        "Leave",
        " ",
        "off",
        " ",
        "that",
        "!",
        "”",
        " ",
        "screamed",
        " ",
        "the",
        " ",
        "Queen",
        ".",
        " ",
        "“",
        "You",
        " ",
        "make",
        " ",
        "me",
        " ",
        "giddy",
        ".",
        "”",
        " ",
        "And",
        " ",
        "then",
        ",",
        " ",
        "turning",
        " ",
        "to",
        " ",
        "the",
        " ",
        "rose",
        "-",
        "tree",
        ",",
        " ",
        "she",
        " ",
        "went",
        " ",
        "on",
        ",",
        " ",
        "“",
        "What",
        " ",
        "have",
        " ",
        "you",
        " ",
        "been",
        " ",
        "doing",
        " ",
        "here",
        "?",
        "”"
      ]
    },
    {
      "type": "paragraph",
      "words": [
        "“",
        "May",
        " ",
        "it",
        " ",
        "please",
        " ",
        "your",
        " ",
        "Majesty",
        ",",
        "”",
        " ",
        "said",
        " ",
        "Two",
        ",",
        " ",
        "in",
        " ",
        "a",
        " ",
        "very",
        " ",
        "humble",
        " ",
        "tone",
        ",",
        " ",
        "going",
        " ",
        "down",
        " ",
        "on",
        " ",
        "one",
        " ",
        "knee",
        " ",
        "as",
        " ",
        "he",
        " ",
        "spoke",
        ",",
        " ",
        "“",
        "we",
        " ",
        "were",
        " ",
        "trying",
        "—",
        "”"
      ]
    },
    {
      "type": "paragraph",
      "words": [
        "“",
        "I",
        " ",
        "see",
        "!",
        "”",
        " ",
        "said",
        " ",
        "the",
        " ",
        "Queen",
        ",",
        " ",
        "who",
        " ",
        "had",
        " ",
        "meanwhile",
        " ",
        "been",
        " ",
        "examining",
        " ",
        "the",
        " ",
        "roses",
        ".",
        " ",
        "“",
        "Off",
        " ",
        "with",
        " ",
        "their",
        " ",
        "heads",
        "!",
        "”",
        " ",
        "and",
        " ",
        "the",
        " ",
        "procession",
        " ",
        "moved",
        " ",
        "on",
        ",",
        " ",
        "three",
        " ",
        "of",
        " ",
        "the",
        " ",
        "soldiers",
        " ",
        "remaining",
        " ",
        "behind",
        " ",
        "to",
        " ",
        "execute",
        " ",
        "the",
        " ",
        "unfortunate",
        " ",
        "gardeners",
        ",",
        " ",
        "who",
        " ",
        "ran",
        " ",
        "to",
        " ",
        "Alice",
        " ",
        "for",
        " ",
        "protection",
        "."
      ]
    },
    {
      "type": "paragraph",
      "words": [
        "“",
        "You",
        " ",
        "shan’t",
        " ",
        "be",
        " ",
        "beheaded",
        "!",
        "”",
        " ",
        "said",
        " ",
        "Alice",
        ",",
        " ",
        "and",
        " ",
        "she",
        " ",
        "put",
        " ",
        "them",
        " ",
        "into",
        " ",
        "a",
        " ",
        "large",
        " ",
        "flower",
        "-",
        "pot",
        " ",
        "that",
        " ",
        "stood",
        " ",
        "near",
        ".",
        " ",
        "The",
        " ",
        "three",
        " ",
        "soldiers",
        " ",
        "wandered",
        " ",
        "about",
        " ",
        "for",
        " ",
        "a",
        " ",
        "minute",
        " ",
        "or",
        " ",
        "two",
        ",",
        " ",
        "looking",
        " ",
        "for",
        " ",
        "them",
        ",",
        " ",
        "and",
        " ",
        "then",
        " ",
        "quietly",
        " ",
        "marched",
        " ",
        "off",
        " ",
        "after",
        " ",
        "the",
        " ",
        "others",
        "."
      ]
    }
  ]
}